README.md
setup.cfg
setup.py
graaf_tools/__init__.py
graaf_tools/embedding.py
graaf_tools/predictors.py
graaf_tools/utils.py
graaf_tools.egg-info/PKG-INFO
graaf_tools.egg-info/SOURCES.txt
graaf_tools.egg-info/dependency_links.txt
graaf_tools.egg-info/requires.txt
graaf_tools.egg-info/top_level.txt
graaf_tools/inducers/__init__.py
graaf_tools/inducers/maxpooling.py
graaf_tools/inducers/nn.py
graaf_tools/inducers/pooling_v1.py