Metadata-Version: 1.1
Name: graaf-tools
Version: 0.4.1
Summary: tools and code for research
Home-page: https://github.com/raftie/graaf_tools
Author: Rafael Van Belle
Author-email: rafael.vanbelle@gmail.com
License: MIT
Download-URL: https://github.com/Raftie/graaf_tools/archive/v0.4.1.tar.gz
Keywords: network
Platform: UNKNOWN
